{
  "url": "https://www.moneycontrol.com/news/business/earnings/gtpl-hathway-standalone-december-2025-net-sales-at-rs-610-03-crore-up-9-69-y-o-y-13770650.html",
  "scraped_at": "2026-01-19T15:16:29.920284",
  "title": "GTPL Hathway Standalone December 2025 Net Sales at Rs 610.03 crore, up 9.69% Y-o-Y",
  "published_date": "January 14, 2026/ 10:52 IST",
  "author": "Broker Research",
  "content": "Reported Standalone quarterly numbers for GTPL Hathway are:Net Sales at Rs 610.03 crore in December 2025 up 9.69% from Rs. 556.16 crore in December 2024. Quarterly Net Profit at Rs. 0.91 crore in December 2025 down 91.5% from Rs. 10.66 crore in December 2024. EBITDA stands at Rs. 58.71 crore in December 2025 down 10.2% from Rs. 65.38 crore in December 2024. GTPL Hathway EPS has decreased to Rs. 0.08 in December 2025 from Rs. 0.95 in December 2024. GTPL Hathway shares closed at 96.60 on January 09, 2026 (NSE) and has given -15.26% returns over the last 6 months and -21.01% over the last 12 months.\n\nGTPL HathwayStandalone Quarterly Resultsin Rs. Cr.\n\nDec'25Sep'25Dec'24Net Sales/Income from operations610.03635.81556.16Other Operating Income------Total Income From Operations610.03635.81556.16EXPENDITUREConsumption of Raw Materials------Purchase of Traded Goods1.554.0614.93Increase/Decrease in Stocks1.04-0.68-7.89Power & Fuel------Employees Cost14.8415.5619.42Depreciation48.3944.6844.58Excise Duty------Admin. And Selling Expenses------R & D Expenses------Provisions And Contingencies------Exp. Capitalised------Other Expenses538.61561.99473.32P/L Before Other Inc. , Int., Excpt. Items & Tax5.6010.2011.80Other Income4.724.429.00P/L Before Int., Excpt. Items & Tax10.3214.6220.80Interest9.107.316.56P/L Before Exceptional Items & Tax1.227.3014.24Exceptional Items------P/L Before Tax1.227.3014.24Tax0.322.053.58P/L After Tax from Ordinary Activities0.915.2510.66Prior Year Adjustments------Extra Ordinary Items------Net Profit/(Loss) For the Period0.915.2510.66Equity Share Capital112.46112.46112.46Reserves Excluding Revaluation Reserves------Equity Dividend Rate (%)------EPS Before Extra OrdinaryBasic EPS0.080.470.95Diluted EPS0.080.470.95EPS After Extra OrdinaryBasic EPS0.080.470.95Diluted EPS0.080.470.95Public Share HoldingNo Of Shares (Crores)------Share Holding (%)------Promoters and Promoter Group Shareholdinga) Pledged/Encumbered- Number of shares (Crores)------- Per. of shares (as a % of the total sh. of prom. and promoter group)------- Per. of shares (as a % of the total Share Cap. of the company)------b) Non-encumbered- Number of shares (Crores)------- Per. of shares (as a % of the total sh. of prom. and promoter group)------- Per. of shares (as a % of the total Share Cap. of the company)------Source :Dion Global Solutions Limited",
  "content_length": 2366,
  "tags": [],
  "category": "business"
}