{
  "url": "https://www.moneycontrol.com/news/business/markets/first-tick-top-global-cues-to-watch-in-today-s-trade-79-13770449.html",
  "scraped_at": "2026-01-19T15:09:48.849709",
  "title": "First Tick: Top global cues to watch in today’s trade",
  "published_date": "January 14, 2026/ 07:35 IST",
  "author": "Rakesh Patil",
  "content": "Indian benchmark indices, Sensex and Nifty, are likely to see a muted start on January 14, with cues coming from GIFT Nifty, which was trading with little change at around 25,760.50.\n\nTrack the latest updates on GIFT Nifty right here on Moneycontrol.\n\nIn another volatile session, the Indian equity market ended lower on January 13, with the Nifty slipping below 25,750 amid selling pressure in auto, consumer durables, pharma and realty stocks.\n\nAt close, the Sensex was down 250.48 points or 0.30 percent at 83,627.69, and the Nifty was down 57.95 points or 0.22 percent at 25,732.30.\n\nThe GIFT Nifty is trading flat at around 25,760.50, indicating a muted opening for the day.\n\nAsian shares posted a modest gain at the open, while Japanese equities extended their record-breaking run fueled by a weaker yen.\n\nUS ​stocks ended lower on Tuesday, led by a drop in financial shares as comments from JPMorgan executives ‌added to worries about US President Donald Trump's recent proposal for a cap on credit‑card rates.\n\nThe Dow Jones Industrial Average fell 398.21 points, ‍or 0.80%, to 49,191.99, the S&P 500 lost 13.53 points, or 0.19%, to 6,963.74 and the Nasdaq Composite lost 24.03 points, or 0.10%, ‌to ‌23,709.87.\n\nThe yield on 10-year Treasuries and 2-year Treasuries was trading with little changed at 4.18% and 3.53%, respectively.\n\nThe US dollar recovered ground to near a one-month high in early Asian trade on Wednesday after US CPI data that was broadly in line with estimates, firming up expectations that the Federal Reserve will remain on hold later this month despite unprecedented pressure from the White House to lower interest rates.\n\nAsian Currencies (Down)\n\nAll the Asian currencies were trading in the red in the early trade on Wednesday, with the Japanese Yen leading the losers, followed by Indonesian Rupiah, Philippine Peso, China Renminbi, Taiwan Dollar, Malaysian Ringgit.\n\nBrent crude notched its biggest four-day gain since June as Trump ramped up rhetoric on Iran.\n\nGold rose toward a record high as weaker-than expected US inflation data supported the case for more interest rate cuts, while the geopolitical situation remained combustible.\n\nOn January 13, the Foreign Institutional Investors (FIIs) sold equities worth around Rs 1499 crore, while Domestic Institutional Investors (DIIs) purchased equities worth Rs 1181 crore.\n\nHope you're all set for today's trade. We wish you a profitable day ahead.\n\nDisclaimer: The views and investment tips expressed by investment experts on Moneycontrol.com are their own and not those of the website or its management. Moneycontrol.com advises users to check with certified experts before taking any investment decisions.",
  "content_length": 2721,
  "tags": [],
  "category": "business"
}